Metadata-Version: 2.1
Name: documatic
Version: 0.8.0
Summary: API interface for generating documentation for Python projects
Home-page: UNKNOWN
Author: Documatic
License: UNKNOWN
Platform: UNKNOWN
